raster2tiles/__init__.py
raster2tiles/cli.py
raster2tiles/database.py
raster2tiles/tile.py
raster2tiles-0.1.0.dist-info/METADATA
raster2tiles-0.1.0.dist-info/WHEEL
raster2tiles-0.1.0.dist-info/entry_points.txt
raster2tiles-0.1.0.dist-info/top_level.txt
raster2tiles-0.1.0.dist-info/RECORD
