Metadata-Version: 2.1
Name: raster2tiles
Version: 0.1.0
Summary: UNKNOWN
Home-page: UNKNOWN
License: UNKNOWN
Platform: UNKNOWN
Requires-Python: >=3
Requires-Dist: cycler (>=0.10.0)
Requires-Dist: decorator (>=4.1.2)
Requires-Dist: enum34 (>=1.1.6)
Requires-Dist: GDAL (==2.2.1)
Requires-Dist: numpy (>=1.13.1)
Requires-Dist: olefile (>=0.44)
Requires-Dist: pexpect (>=4.2.1)
Requires-Dist: pickleshare (>=0.7.4)
Requires-Dist: Pillow (>=4.2.1)
Requires-Dist: prompt-toolkit (>=1.0.15)
Requires-Dist: psycopg2 (>=2.7.3.1)
Requires-Dist: ptyprocess (>=0.5.2)
Requires-Dist: Pygments (>=2.2.0)
Requires-Dist: pyparsing (>=2.2.0)
Requires-Dist: python-dateutil (>=2.6.1)
Requires-Dist: pytz (>=2017.2)
Requires-Dist: scandir (>=1.5)
Requires-Dist: scipy (>=0.19.1)
Requires-Dist: simplegeneric (>=0.8.1)
Requires-Dist: six (>=1.10.0)
Requires-Dist: SQLAlchemy (>=1.2.0b2)
Requires-Dist: traitlets (>=4.3.2)
Requires-Dist: wcwidth (>=0.1.7)
